nandist/__init__.py
nandist/cdist.py
nandist/functions.py
nandist/pdist.py
nandist-0.12.0.dist-info/LICENSE
nandist-0.12.0.dist-info/WHEEL
nandist-0.12.0.dist-info/METADATA
nandist-0.12.0.dist-info/RECORD
