Metadata-Version: 2.1
Name: nandist
Version: 0.12.0
Summary: Compute distances in numpy arrays with nans
Author-email: Wouter Donders <wouter@42analytics.eu>
Requires-Python: >=3.8
Classifier: Development Status :: 4 - Beta
Classifier: Natural Language :: English
Classifier: Operating System :: OS Independent
Classifier: Programming Language :: Python
Classifier: Programming Language :: Python :: 3.8
Classifier: Programming Language :: Python :: 3.9
Classifier: Programming Language :: Python :: 3.10
Classifier: Programming Language :: Python :: 3.11
Classifier: License :: OSI Approved :: BSD License
Classifier: Topic :: Scientific/Engineering :: Mathematics
Requires-Dist: scipy>=1.9.0
Requires-Dist: flit ~= 3.8 ; extra == "build"
Requires-Dist: twine ~= 4.0 ; extra == "build"
Requires-Dist: bump2version ~= 1.0 ; extra == "dev"
Requires-Dist: flit ~= 3.8 ; extra == "dev"
Requires-Dist: hypothesis[numpy] ~= 6.61.0 ; extra == "dev"
Requires-Dist: pre-commit ~= 2.20 ; extra == "dev"
Requires-Dist: pytest ~= 7.2 ; extra == "dev"
Requires-Dist: tox ~= 3.27 ; extra == "dev"
Requires-Dist: sphinx ~= 5.3.0 ; extra == "docs"
Requires-Dist: sphinx-rtd-theme ~= 1.1.1 ; extra == "docs"
Requires-Dist: hypothesis[numpy] ~= 6.61.0 ; extra == "test"
Requires-Dist: pytest ~= 7.2 ; extra == "test"
Requires-Dist: tox ~= 3.27 ; extra == "test"
Project-URL: Documentations, https://42analytics1.gitlab.io/public/nandist/
Project-URL: Download, https://gitlab.com/42analytics1/public/nandist/-/packages
Project-URL: Homepage, https://42analytics.eu
Project-URL: Source, https://gitlab.com/42analytics1/public/nandist
Project-URL: Tracker, https://gitlab.com/42analytics1/public/nandist/-/issues
Provides-Extra: build
Provides-Extra: dev
Provides-Extra: docs
Provides-Extra: test
